weaktree/__init__.py
weaktree/node.py
weaktree/py.typed
weaktree/types.py
weaktree-0.1.0.dist-info/licenses/LICENSE
weaktree-0.1.0.dist-info/METADATA
weaktree-0.1.0.dist-info/WHEEL
weaktree-0.1.0.dist-info/top_level.txt
weaktree-0.1.0.dist-info/RECORD
