Metadata-Version: 2.4
Name: weaktree
Version: 0.1.0
Summary: A self-pruning, weak-referencing tree structure.
Author-email: BetterBuiltFool <betterbuiltfool@gmail.com>
Classifier: Programming Language :: Python :: 3
Classifier: License :: OSI Approved :: MIT License
Classifier: Operating System :: OS Independent
Classifier: Topic :: Utilities
Classifier: Typing :: Typed
Requires-Python: >=3.12.4
License-File: LICENSE
Dynamic: license-file
